{"client":"Thunder Client","collectionName":"RDP APIs Collection","dateExported":"2021-07-15T04:33:11.076Z","version":"1.1","folders":[{"containerId":"","sortNum":20000,"name":"Authentication","_id":"11947f78-526b-4926-80b3-8356c662225f","created":"2021-07-15T04:32:53.210Z"},{"containerId":"","sortNum":30000,"name":"ESG","_id":"0ebb7499-fe36-49c0-99f1-d43afa2ddf83","created":"2021-07-15T04:32:53.210Z"},{"containerId":"","sortNum":40000,"name":"Symbology","_id":"87b623cd-8ce1-4564-8b27-48532d06bb7b","created":"2021-07-15T04:32:53.210Z"},{"containerId":"","sortNum":50000,"name":"IPA","_id":"d771d675-224c-4351-87f4-b348e851f690","created":"2021-07-15T04:32:53.210Z"}],"requests":[{"containerId":"11947f78-526b-4926-80b3-8356c662225f","sortNum":10000,"headers":[{"name":"Accept","value":"*/*"},{"name":"User-Agent","value":"Thunder Client (https://www.thunderclient.io)"}],"colId":"117c5288-f5c6-4c4b-82df-6cec53fe9b87","name":"RDP APIs Auth","url":"https://{{rdp_host}}/auth/oauth2/{{rdp_version_auth}}/token","method":"POST","modified":"2021-07-15T04:32:53.212Z","created":"2021-07-15T04:32:53.212Z","_id":"02527cd6-9a0f-4f8a-8855-eb8fa11fb9dc","params":[],"body":{"type":"formencoded","raw":"","form":[{"name":"username","value":"{{username}}"},{"name":"password","value":"{{password}}"},{"name":"client_id","value":"{{app_key}}"},{"name":"grant_type","value":"password"},{"name":"takeExclusiveSignOnControl","value":"true"},{"name":"scope","value":"trapi"}]},"tests":[{"type":"res-code","custom":"","action":"equal","value":"200"},{"type":"Content-Type","custom":"","action":"equal","value":"application/json"},{"type":"set-env-var","custom":"json.access_token","action":"setto","value":"{{access_token}}"},{"type":"set-env-var","custom":"json.refresh_token","action":"setto","value":"{{refresh_token}}"}]},{"containerId":"0ebb7499-fe36-49c0-99f1-d43afa2ddf83","sortNum":20000,"headers":[{"name":"Accept","value":"*/*"},{"name":"User-Agent","value":"Thunder Client (https://www.thunderclient.io)"}],"colId":"117c5288-f5c6-4c4b-82df-6cec53fe9b87","name":"ESG - Basic","url":"https://{{rdp_host}}/data/environmental-social-governance/{{rdp_version_esg}}/views/basic?universe={{symbol}}","method":"GET","modified":"2021-07-15T04:32:53.212Z","created":"2021-07-15T04:32:53.212Z","_id":"42969ad9-c111-4813-87e0-ab4c09cd096d","params":[{"name":"universe","value":"{{symbol}}"}],"auth":{"type":"bearer","bearer":"{{access_token}}"},"tests":[{"type":"res-code","custom":"","action":"equal","value":"200"},{"type":"Content-Type","custom":"","action":"equal","value":"application/json; charset=utf-8"}]},{"containerId":"0ebb7499-fe36-49c0-99f1-d43afa2ddf83","sortNum":30000,"headers":[{"name":"Accept","value":"*/*"},{"name":"User-Agent","value":"Thunder Client (https://www.thunderclient.io)"}],"colId":"117c5288-f5c6-4c4b-82df-6cec53fe9b87","name":"ESG - Score Full","url":"https://{{rdp_host}}/data/environmental-social-governance/{{rdp_version_esg}}/views/scores-full?universe={{symbol}}","method":"GET","modified":"2021-07-15T04:32:53.212Z","created":"2021-07-15T04:32:53.212Z","_id":"55effa42-c6aa-4376-8d6d-507c2d1b33fb","params":[{"name":"universe","value":"{{symbol}}"}],"auth":{"type":"bearer","bearer":"{{access_token}}"},"tests":[{"type":"res-code","custom":"","action":"equal","value":"200"},{"type":"Content-Type","custom":"","action":"equal","value":"application/json; charset=utf-8"}]},{"containerId":"87b623cd-8ce1-4564-8b27-48532d06bb7b","sortNum":40000,"headers":[{"name":"Accept","value":"*/*"},{"name":"User-Agent","value":"Thunder Client (https://www.thunderclient.io)"}],"colId":"117c5288-f5c6-4c4b-82df-6cec53fe9b87","name":"Identifier to multiple identifiers","url":"https://{{rdp_host}}/discovery/symbology/{{rdp_version_symbology}}/lookup","method":"POST","modified":"2021-07-15T04:32:53.212Z","created":"2021-07-15T04:32:53.212Z","_id":"5dcb86e1-63eb-4b17-9af3-3bf27985d8ac","params":[],"body":{"type":"json","raw":"{\n  \"from\": [\n    {\n      \"identifierTypes\": [\n        \"RIC\"\n      ],\n      \"values\": [\n        \"TWTR.N\",\n        \"FB.O\"\n      ]\n    }\n  ],\n  \"to\": [\n    {\n      \"identifierTypes\": [\n        \"ISIN\",\n        \"SEDOL\"\n      ]\n    }\n  ],\n  \"type\": \"auto\"\n}","form":[]},"auth":{"type":"bearer","bearer":"{{access_token}}"},"tests":[{"type":"res-code","custom":"","action":"equal","value":"200"},{"type":"Content-Type","custom":"","action":"equal","value":"application/json"}]},{"containerId":"11947f78-526b-4926-80b3-8356c662225f","sortNum":50000,"headers":[{"name":"Accept","value":"*/*"},{"name":"User-Agent","value":"Thunder Client (https://www.thunderclient.io)"}],"colId":"117c5288-f5c6-4c4b-82df-6cec53fe9b87","name":"RDP APIs Auth - Refresh Token","url":"https://{{rdp_host}}/auth/oauth2/{{rdp_version_auth}}/token","method":"POST","modified":"2021-07-15T04:32:53.212Z","created":"2021-07-15T04:32:53.212Z","_id":"72f6e1c2-3d39-45b6-8fc0-008f68902a3f","params":[],"body":{"type":"formencoded","raw":"","form":[{"name":"refresh_token","value":"{{refresh_token}}"},{"name":"username","value":"{{username}}"},{"name":"grant_type","value":"refresh_token"},{"name":"client_id","value":"{{app_key}}"}]},"tests":[{"type":"res-code","custom":"","action":"equal","value":"200"},{"type":"Content-Type","custom":"","action":"equal","value":"application/json"},{"type":"set-env-var","custom":"json.access_token","action":"setto","value":"{{access_token}}"},{"type":"set-env-var","custom":"json.refresh_token","action":"setto","value":"{{refresh_token}}"}]},{"containerId":"d771d675-224c-4351-87f4-b348e851f690","sortNum":60000,"headers":[{"name":"Accept","value":"*/*"},{"name":"User-Agent","value":"Thunder Client (https://www.thunderclient.io)"}],"colId":"117c5288-f5c6-4c4b-82df-6cec53fe9b87","name":"Financial contracts - FX Forward","url":"https://{{rdp_host}}/data/quantitative-analytics/{{rdp_version_ipa}}/financial-contracts","method":"POST","modified":"2021-07-15T04:32:53.212Z","created":"2021-07-15T04:32:53.212Z","_id":"b1517410-6eef-4321-8b98-c893049b55a2","params":[],"body":{"type":"json","raw":"{\n  \"fields\": [ \"InstrumentTag\", \"StartDate\", \"EndDate\", \"FxSpot\", \"FxSwapsCcy1Ccy2\", \"FxOutrightCcy1Ccy2\" ],\n  \"outputs\": [ \"Data\", \"Headers\" ],\n  \"universe\": [\n    {\n      \"instrumentType\": \"FxCross\",\n      \"instrumentDefinition\": {\n        \"instrumentTag\": \"FX_deal_001\",\n        \"fxCrossType\": \"FxForward\",\n        \"fxCrossCode\": \"EURGBP\",\n        \"legs\": [ { \"tenor\": \"3M10D\" } ]\n      },\n      \"pricingParameters\": {\n        \"valuationDate\": \"2019-02-02T00:00:00Z\",\n        \"priceSide\": \"Mid\"\n      }\n    }\n  ]\n}","form":[]},"auth":{"type":"bearer","bearer":"{{access_token}}"},"tests":[{"type":"res-code","custom":"","action":"equal","value":"200"},{"type":"Content-Type","custom":"","action":"equal","value":"application/json"}]},{"containerId":"87b623cd-8ce1-4564-8b27-48532d06bb7b","sortNum":70000,"headers":[{"name":"Accept","value":"*/*"},{"name":"User-Agent","value":"Thunder Client (https://www.thunderclient.io)"}],"colId":"117c5288-f5c6-4c4b-82df-6cec53fe9b87","name":"Identifier to PermID","url":"https://{{rdp_host}}/discovery/symbology/{{rdp_version_symbology}}/lookup","method":"POST","modified":"2021-07-15T04:32:53.212Z","created":"2021-07-15T04:32:53.212Z","_id":"02452089-8acf-4c92-9a23-1a01b9965fac","params":[],"body":{"type":"json","raw":"{\n  \"from\": [\n    {\n      \"identifierTypes\": [\n        \"RIC\"\n      ],\n      \"values\": [\n        \"7203.T\",\n        \"{{symbol}}\"\n      ]\n    }\n  ],\n  \"to\": [\n    {\n      \"objectTypes\": [\n        \"organization\"\n      ],\n      \"identifierTypes\": [\n        \"PermID\"\n      ]\n    }\n  ],\n  \"type\": \"auto\"\n}","form":[]},"auth":{"type":"bearer","bearer":"{{access_token}}"},"tests":[{"type":"res-code","custom":"","action":"equal","value":"200"},{"type":"Content-Type","custom":"","action":"equal","value":"application/json"}]}]}
